{
  "content": "<h1>勇做独特的自己，踏出专属之路</h1>\n<p>在这光怪陆离的世界舞台上，我们犹如星辰般各自闪烁，却又常常被外界的目光和期待所牵引。社会的既定框架、他人无形的评判标准，仿佛一张张细密的网，试图将我们规训成千篇一律的模样。然而，真正的自由与幸福，恰似隐匿于重重迷雾后的宝藏，唯有勇敢地做自己，笃定地踏上属于自己的道路，方能寻得。</p>\n<h2>剖析自我，珍视独特印记</h2>\n<h3>聆听内心的低语</h3>\n<p>每个人都是一个独立而神秘的小宇宙，怀揣着独一无二的思想、情感与梦想。可在生活的洪流中，外界的嘈杂声常常淹没我们内心的声音。就像在一场盛大的音乐会上，周围激昂的旋律容易让我们忽略自己心底那微弱却独特的音符。</p>\n<p>学会在喧嚣中静下心来，深入探索内心的世界，是我们认识自我的关键一步。当我们抛开外界的纷扰，静下心审视自己的兴趣爱好，比如有人热爱在清晨的公园里慢跑，感受汗水与微风的交织；有人钟情于在午后的书房里沉浸于一本好书，与文字进行灵魂的对话。这些看似平常的喜好，实则是我们内心真实渴望的外在体现，它们往往与他人的期待毫无关联。</p>\n<h3>拥抱自身的不完美</h3>\n<p>金无足赤，人无完人。每个人都是优点与不足的奇妙组合，这恰恰构成了我们独一无二的个性。然而，很多人却因害怕他人的批评或嘲笑，如鸵鸟般将头埋进沙子，试图隐藏自己的缺点。</p>\n<p>事实上，只有勇敢地接纳自己的不完美，才能真正地做自己。就像断臂维纳斯，她的残缺并未影响她的美感，反而赋予了她独特的艺术魅力。当我们能够正视自己的不足，并努力改进时，就如同给璞玉雕琢，会让自己变得更加自信和坚强。</p>\n<h2>直面外界质疑，坚守内心灯塔</h2>\n<h3>筑牢信念之基</h3>\n<p>当我们毅然选择走自己的路时，外界的质疑和反对声便会如潮水般涌来。此时，坚定的信念便是我们抵御风浪的坚固堤坝。</p>\n<p>历史上无数伟大的人物用他们的亲身经历为我们诠释了这一点。比如，梵高在那个传统绘画观念占据主导的时代，坚持自己独特的绘画风格，不被当时的主流审美所左右。尽管他生前饱受质疑和贫困的折磨，但他始终坚信自己的艺术理念，最终他的作品在后世绽放出耀眼的光芒，成为现代艺术的经典之作。</p>\n<h3>巧应批评之箭</h3>\n<p>面对外界的质疑，批评声在所难免。但换个角度看，批评并非全是坏事，它就像一面镜子，能让我们从不同的视角审视自己，发现那些隐藏在角落的不足之处。</p>\n<p>当我们受到批评时，切不可急于反驳，而是要像冷静的猎手，先让情绪的野兽平静下来，然后仔细分析批评的内容。从中筛选出有益的建议，为自己所用。同时，我们也要练就一双慧眼，区分建设性的批评和恶意的攻击。对于那些毫无根据的无端指责，大可一笑而过，让其在时光的长河中自生自灭。</p>\n<h2>勇闯自己的路，绽放独特光芒</h2>\n<h3>挖掘无限潜力</h3>\n<p>每个人都是一座尚未完全开发的宝藏，蕴含着无限的潜力。只要我们有勇气迈出舒适区，勇于挑战自我，就能像探险家发现新大陆一样，挖掘出自身潜藏的能力。</p>\n<p>走自己的路，意味着我们要不断地探索未知领域，尝试新的事物。就像马斯克，他敢于涉足电动汽车、太空探索等多个看似遥不可及的领域。在这个过程中，他遭遇了无数次的失败和挫折，但正是这些经历让他不断突破自我，创造出一个个令人惊叹的奇迹。</p>\n<h3>回馈社会价值</h3>\n<p>当我们沿着自己的道路前行，实现个人梦想的同时，也要心怀社会，关注社会的需求，为社会创造价值。</p>\n<p>一个人的价值不仅仅体现在个人的成就上，更在于他对社会的贡献。比如，袁隆平院士一生致力于杂交水稻研究，他用自己的智慧和汗水，解决了无数人的温饱问题，为世界粮食安全做出了巨大贡献。他的生命因这份无私的奉献而变得更加熠熠生辉。</p>\n<h2>涵养积极心态，畅享人生旅程</h2>\n<h3>秉持乐观态度</h3>\n<p>在走自己的路的过程中，困难和挑战就像路上的绊脚石，无处不在。此时，保持乐观的态度就如同手持明灯，照亮前行的道路。</p>\n<p>乐观的心态能让我们在面对困难时，依然保持积极向上的精神状态，激发我们的创造力和解决问题的能力。就像苏轼一生多次被贬，但他始终能以乐观豁达的心态面对生活的种种不如意，在困境中创作出许多流传千古的佳作。</p>\n<h3>领略过程之美</h3>\n<p>走自己的路，不仅仅是为了抵达最终的目标，更重要的是享受过程中的每一个瞬间。无论是成功的喜悦，还是失败的痛苦，都是人生这部宏大乐章中不可或缺的音符。</p>\n<p>学会享受过程，我们会发现生活中处处都充满了美好。就像一场旅行，目的地固然重要，但沿途的风景、与陌生人的邂逅、内心的感悟，才是旅行真正的意义所在。</p>\n<p>不要害怕做与众不同的自己，勇敢地踏出属于自己的道路。在这个充满机遇与挑战的时代，唯有勇敢地追逐梦想，坚定地走自己的路，我们才能书写出属于自己的精彩人生篇章。让我们一同拥抱独特的自己，向着未知的前方，无畏前行！</p>\n",
  "meta": {
    "title": "勇做独特的自己，踏出专属之路",
    "category": "自我提升",
    "tags": [
      "独特自我",
      "社会压力",
      "坚守信念",
      "挖掘潜力",
      "回馈社会"
    ],
    "description": "阐述在复杂的社会环境中，如何剖析自我、直面外界质疑，勇敢地踏出属于自己的道路，挖掘潜力、创造价值并涵养积极心态，实现个人的成长与自我实现。"
  }
}